mediaferry/__init__.py
mediaferry/__version__.py
mediaferry/config.py
mediaferry/download.py
mediaferry/main.py
mediaferry-0.2.2.dist-info/entry_points.txt
mediaferry-0.2.2.dist-info/licenses/LICENSE
mediaferry-0.2.2.dist-info/METADATA
mediaferry-0.2.2.dist-info/WHEEL
mediaferry-0.2.2.dist-info/RECORD
