Metadata-Version: 2.4
Name: mediaferry
Version: 0.2.2
Summary: yt-dlp download management tool
License-File: LICENSE
Author: DigitalDragon
Requires-Python: >=3.10
Classifier: Programming Language :: Python :: 3
Classifier: Programming Language :: Python :: 3.10
Classifier: Programming Language :: Python :: 3.11
Classifier: Programming Language :: Python :: 3.12
Classifier: Programming Language :: Python :: 3.13
Classifier: Programming Language :: Python :: 3.14
Requires-Dist: dataclasses-json
Requires-Dist: humanize
Requires-Dist: internetarchive (>=5.0.3)
Requires-Dist: yt-dlp (>=2025.12.8)
Project-URL: Repository, https://github.com/DigitalDwagon/MediaFerry
